quicksocketpy/__init__.py
quicksocketpy-0.0.6.dist-info/METADATA
quicksocketpy-0.0.6.dist-info/WHEEL
quicksocketpy-0.0.6.dist-info/RECORD
