Metadata-Version: 2.4
Name: quicksocketpy
Version: 0.0.6
Summary: 
Requires-Python: >=3.13
Classifier: Programming Language :: Python :: 3
Classifier: Programming Language :: Python :: 3.13
Classifier: Programming Language :: Python :: 3.14
Requires-Dist: dill
